{
  "title": "Arenales de San Gregorio",
  "url": "https://en.wikipedia.org/wiki/Arenales_de_San_Gregorio",
  "body": "Arenales de San Gregorio is a municipality in the province of Ciudad Real, Castile-La Mancha, Spain. It has a population of 703.\nEconomy is mostly based on agriculture, with cultivation of vine and olives.\n\n\n\nThe village economy is mainly based on the primary sector. The cultivation of vineyards and olive cultivation are very importants. But the most important product of the village is the fabulous melon cultivation.\nThe village has also a cooperative, bars and a rural hotel.\n\n\n",
  "links": [
    "Aben\u00f3jar, Ciudad Real",
    "Agudo, Ciudad Real",
    "Alamillo",
    "Albaladejo",
    "Alcoba",
    "Alcolea de Calatrava",
    "Alcubillas",
    "Alc\u00e1zar de San Juan",
    "Aldea del Rey",
    "Alhambra, Ciudad Real",
    "Almadenejos",
    "Almad\u00e9n",
    "Almagro, Ciudad Real",
    "Almedina",
    "Almod\u00f3var del Campo",
    "Almuradiel",
    "Anchuras",
    "Arenas de San Juan",
    "Argamasilla de Alba",
    "Argamasilla de Calatrava",
    "Arroba de los Montes",
    "Autonomous communities of Spain",
    "Ballesteros de Calatrava",
    "Bola\u00f1os de Calatrava",
    "Brazatortas",
    "Cabezarados",
    "Cabezarrubias del Puerto",
    "Calzada de Calatrava",
    "Campo de Criptana",
    "Caracuel de Calatrava",
    "Carrizosa",
    "Carri\u00f3n de Calatrava",
    "Castellar de Santiago",
    "Castile-La Mancha",
    "Castilla\u2013La Mancha",
    "Ca\u00f1ada de Calatrava",
    "Central European Summer Time",
    "Central European Time",
    "Chill\u00f3n",
    "Ciudad Real",
    "Coat of arms of Arenales de San Gregorio",
    "Comarcas of Spain",
    "Corral de Calatrava",
    "C\u00f3zar",
    "Daimiel",
    "Daylight saving time",
    "Demonym",
    "El Robledo",
    "Fern\u00e1n Caballero, Ciudad Real",
    "Flag of Arenales de San Gregorio",
    "Fontanarejo",
    "Fuencaliente, Ciudad Real",
    "Fuenllana",
    "Fuente el Fresno",
    "Gran\u00e1tula de Calatrava",
    "Guadalmez",
    "Herencia",
    "Hinojosas de Calatrava",
    "Horcajo de los Montes",
    "Instituto Nacional de Estad\u00edstica (Spain)",
    "Judicial districts of Spain",
    "La Solana",
    "Languages of Spain",
    "Las Labores",
    "List of municipalities in Ciudad Real",
    "List of postal codes in Spain",
    "Llanos del Caudillo",
    "Los Cortijos",
    "Los Pozuelos de Calatrava",
    "Luciana, Ciudad Real",
    "Malag\u00f3n",
    "Mancha Alta",
    "Manzanares, Ciudad Real",
    "Membrilla",
    "Mestanza",
    "Miguelturra",
    "Montiel",
    "Moral de Calatrava",
    "Municipalities of Spain",
    "Navalpino",
    "Navas de Estena",
    "Pedro Mu\u00f1oz",
    "Pic\u00f3n",
    "Piedrabuena",
    "Poblete",
    "Porzuna",
    "Pozuelo de Calatrava",
    "Province of Ciudad Real",
    "Provinces of Spain",
    "Puebla de Don Rodrigo",
    "Puebla del Pr\u00edncipe",
    "Puerto L\u00e1pice",
    "Puertollano",
    "Retuerta del Bullaque",
    "Ruidera",
    "Saceruela",
    "San Carlos del Valle",
    "San Lorenzo de Calatrava",
    "Santa Cruz de Mudela",
    "Santa Cruz de los C\u00e1\u00f1amos",
    "Socu\u00e9llamos",
    "Solana del Pino",
    "Spain",
    "Terrinches",
    "Time zone",
    "Tomelloso",
    "Torralba de Calatrava",
    "Torre de Juan Abad",
    "Torrenueva",
    "UTC+1",
    "UTC+2",
    "VIAF (identifier)",
    "Valdemanco del Esteras",
    "Valdepe\u00f1as",
    "Valenzuela de Calatrava",
    "Villahermosa, Ciudad Real",
    "Villamanrique",
    "Villamayor de Calatrava",
    "Villanueva de San Carlos",
    "Villanueva de la Fuente",
    "Villanueva de los Infantes, Ciudad Real",
    "Villar del Pozo",
    "Villarrubia de los Ojos",
    "Villarta de San Juan",
    "Viso del Marqu\u00e9s"
  ],
  "images": [
    "https://upload.wikimedia.org/wikipedia/commons/d/d4/Bandera_Castilla-La_Mancha.svg",
    "https://upload.wikimedia.org/wikipedia/commons/1/1f/Bandera_de_Arenales_de_San_Gregorio_%28Ciudad_Real%29.svg",
    "https://upload.wikimedia.org/wikipedia/commons/2/2e/Escudo_de_Arenales_de_San_Gregorio_%28Ciudad_Real%29.svg",
    "https://upload.wikimedia.org/wikipedia/commons/3/30/Flag_map_of_Castile-La_Mancha.svg",
    "https://upload.wikimedia.org/wikipedia/commons/3/36/Iglesia_de_arenales.jpg",
    "https://upload.wikimedia.org/wikipedia/commons/0/0c/Red_pog.svg",
    "https://upload.wikimedia.org/wikipedia/commons/3/39/Spain_location_map_with_provinces.svg",
    "https://upload.wikimedia.org/wikipedia/en/9/9a/Flag_of_Spain.svg",
    "https://upload.wikimedia.org/wikipedia/en/8/8a/OOjs_UI_icon_edit-ltr-progressive.svg"
  ]
}