{
  "title": "Thomas Daniel Winter",
  "url": "https://en.wikipedia.org/wiki/Thomas_Daniel_Winter",
  "body": "Thomas Daniel Winter (July 7, 1896 \u2013 November 7, 1951) was a U.S. Representative from Kansas.\nBorn in Columbus, Kansas, Winter attended the public and high schools. During the First World War served as a private in the United States Army Air Service in 1918 and 1919. Court reporter of the district court of Crawford County, Kansas from 1921 to 1927. He studied law and was admitted to the bar in 1926 and commenced practice in Girard, Kansas.\nHe served as assistant county attorney of Crawford County, Kansas, in 1927 and 1928 and county attorney in 1929 and 1930. He served as commissioner of public utilities of Girard 1933\u20131935. He served as commissioner of finance of Girard 1936\u20131938.\nWinter was elected as a Republican to the Seventy-sixth and to the three succeeding Congresses (January 3, 1939 \u2013 January 3, 1947). He was an unsuccessful candidate for renomination in 1946. He returned to Girard, Kansas, and continued to practice law. He died in Pittsburg, Kansas, November 7, 1951 and is interred in Park Cemetery, Columbus, Kansas.\n\n\n\nUnited States Congress. \"Thomas Daniel Winter (id: W000645)\". Biographical Directory of the United States Congress. This article incorporates public domain material from the Biographical Directory of the United States Congress.",
  "links": [
    "76th United States Congress",
    "Abel Carter Wilder",
    "Admission to the bar in the United States",
    "Albert M. Cole",
    "Alexander C. Mitchell",
    "Alfred Metcalf Jackson",
    "Benjamin H. Clover",
    "Biographical Directory of the United States Congress",
    "Bishop W. Perkins",
    "Bob Dole",
    "Bob Whittaker",
    "Case Broderick",
    "Charles Curtis",
    "Charles Frederick Scott",
    "Charles I. Sparks",
    "Chauncey B. Little",
    "Chester I. Long",
    "Chester L. Mize",
    "Clifford R. Hope",
    "Columbus, Kansas",
    "Copyright status of works by the federal government of the United States",
    "Crawford County, Kansas",
    "Dan Glickman",
    "Daniel Read Anthony Jr.",
    "David Perley Lowe",
    "Dennis Moore (politician)",
    "Denver David Hargis",
    "Dick Nichols",
    "Dudley C. Haskell",
    "Dudley Doolittle",
    "Edmond H. Madison",
    "Edmund Needham Morrill",
    "Edward C. Little",
    "Edward H. Funston",
    "Edward Herbert Rees",
    "Edward W. Patterson",
    "Edward White Patterson",
    "Edwin R. Ridgely",
    "Erastus J. Turner",
    "Errett P. Scrivner",
    "Frank Carlson",
    "Fred S. Jackson",
    "Garner E. Shriver",
    "George A. Neeley",
    "Girard, Kansas",
    "Guy T. Helvering",
    "Harold C. McGugin",
    "Harrison Kelley",
    "Hays B. White",
    "Herbert A. Meyer",
    "Herbert Alton Meyer",
    "Homer Hoch",
    "Horace Ladd Moore",
    "Howard Shultz Miller",
    "Isaac D. Young",
    "Jake LaTurner",
    "James Edmund Jeffries",
    "James Floyd Breeding",
    "James G. Strong",
    "James Monroe Miller",
    "Jan Meyers",
    "Jasper N. Tincher",
    "Jeremiah D. Botkin",
    "Jerry Moran",
    "Jerry Simpson",
    "Jim Ryun",
    "Jim Slattery",
    "Joe Skubitz",
    "John Alexander Anderson",
    "John Davis (Kansas politician)",
    "John G. Otis",
    "John Mills Houston",
    "John R. Connelly",
    "John R. Goodin",
    "John Wilkins Whitfield",
    "Joseph Taggart",
    "Jouett Shouse",
    "Justin De Witt Bowersock",
    "Kansas",
    "Kansas's 1st congressional district",
    "Kansas's 2nd congressional district",
    "Kansas's 3rd congressional district",
    "Kansas's 4th congressional district",
    "Kansas's 5th congressional district",
    "Kansas's 6th congressional district",
    "Kansas's 7th congressional district",
    "Kansas's 8th congressional district",
    "Kansas's at-large congressional district",
    "Kansas Territory's at-large congressional district",
    "Kathryn O'Loughlin McCarthy",
    "Keith Sebelius",
    "Kevin Yoder",
    "Larry Winn",
    "Lewis Hanback",
    "List of United States representatives from Kansas",
    "Lynn Jenkins",
    "Marcus Junius Parrott",
    "Martha Keys",
    "Martin F. Conway",
    "Mason S. Peters",
    "Mike Pompeo",
    "Myron V. George",
    "Nancy Boyda",
    "Nelson B. McCormick",
    "Newell A. George",
    "Orrin Larrabee Miller",
    "Pat Roberts",
    "Philip P. Campbell",
    "Pittsburg, Kansas",
    "Randolph Carpenter",
    "Republican Party (United States)",
    "Richard Ely Bird",
    "Richard W. Blue",
    "Robert Ellsworth",
    "Roger Marshall (politician)",
    "Rollin R. Rees",
    "Ron Estes",
    "Sam Brownback",
    "Samuel R. Peters",
    "Sharice Davids",
    "Sidney Clarke",
    "Snyder S. Kirkpatrick",
    "Stephen A. Cobb",
    "Steve Watkins",
    "Thomas Jefferson Hudson",
    "Thomas Ryan (Kansas politician)",
    "Thomas Winter (disambiguation)",
    "Tim Huelskamp",
    "Todd Tiahrt",
    "Tracey Mann",
    "Ulysses Samuel Guyer",
    "United States Army Air Service",
    "United States House of Representatives",
    "Victor Murdock",
    "Vince Snowbarger",
    "Walter Lewis McVey, Jr.",
    "William A. Calderhead",
    "William A. Phillips",
    "William Alexander Harris (Kansas politician)",
    "William Augustus Ayres",
    "William Augustus Reeder",
    "William Baker (Kansas politician)",
    "William D. Vincent",
    "William H. Avery (politician)",
    "William H. Sproul",
    "William P. Lambertson",
    "William R. Roy",
    "William Ripley Brown",
    "Willis J. Bailey",
    "Wint Smith"
  ],
  "images": [
    "https://upload.wikimedia.org/wikipedia/commons/d/da/Flag_of_Kansas.svg",
    "https://upload.wikimedia.org/wikipedia/commons/1/1a/Seal_of_the_United_States_House_of_Representatives.svg",
    "https://upload.wikimedia.org/wikipedia/commons/e/e1/Thomas_Daniel_Winter.jpg",
    "https://upload.wikimedia.org/wikipedia/en/8/8a/OOjs_UI_icon_edit-ltr-progressive.svg",
    "https://upload.wikimedia.org/wikipedia/en/6/62/PD-icon.svg"
  ]
}